flowstrider/__init__.py
flowstrider/settings.py
flowstrider/storage.py
flowstrider/tool.py
flowstrider/converters/__init__.py
flowstrider/converters/dfd_to_dot_converter.py
flowstrider/converters/metadata_xsxl_converter.py
flowstrider/converters/threats_to_file_converter.py
flowstrider/helpers/__init__.py
flowstrider/helpers/warnings.py
flowstrider/localization/attributes/input_files.txt
flowstrider/localization/attributes/de/LC_MESSAGES/attributes.mo
flowstrider/localization/attributes/de/LC_MESSAGES/attributes.po
flowstrider/localization/attributes/en/LC_MESSAGES/attributes.mo
flowstrider/localization/attributes/en/LC_MESSAGES/attributes.po
flowstrider/localization/linddun/input_files.txt
flowstrider/localization/linddun/de/LC_MESSAGES/linddun.mo
flowstrider/localization/linddun/de/LC_MESSAGES/linddun.po
flowstrider/localization/linddun/en/LC_MESSAGES/linddun.mo
flowstrider/localization/linddun/en/LC_MESSAGES/linddun.po
flowstrider/localization/messages/input_files.txt
flowstrider/localization/messages/de/LC_MESSAGES/messages.mo
flowstrider/localization/messages/de/LC_MESSAGES/messages.po
flowstrider/localization/messages/en/LC_MESSAGES/messages.mo
flowstrider/localization/messages/en/LC_MESSAGES/messages.po
flowstrider/models/__init__.py
flowstrider/models/common_models.py
flowstrider/models/dataflowdiagram.py
flowstrider/models/threat.py
flowstrider/models/threat_management.py
flowstrider/rules/__init__.py
flowstrider/rules/attributes_dict.py
flowstrider/rules/collections.py
flowstrider/rules/common_rules.py
flowstrider/rules/elicit.py
flowstrider/rules/builtin/__init__.py
flowstrider/rules/builtin/bsi_rules/__init__.py
flowstrider/rules/builtin/bsi_rules/bsi_rule_collection.py
flowstrider/rules/builtin/linddun_rules/__init__.py
flowstrider/rules/builtin/linddun_rules/linddun_rule_collection.py
flowstrider/rules/builtin/stride_rules/__init__.py
flowstrider/rules/builtin/stride_rules/generic_stride_rule_collection.py
flowstrider-1.1.0.dist-info/licenses/LICENSE.txt
flowstrider-1.1.0.dist-info/METADATA
flowstrider-1.1.0.dist-info/WHEEL
flowstrider-1.1.0.dist-info/entry_points.txt
flowstrider-1.1.0.dist-info/top_level.txt
flowstrider-1.1.0.dist-info/RECORD
