Metadata-Version: 2.4
Name: flowstrider
Version: 1.1.0
Summary: FlowStrider automates data flow-based threat modeling
Home-page: https://github.com/pyscaffold/pyscaffold/
Author: Clemens-Alexander Brust, Bernd Gruner, Noah Erthel
Author-email: clemens-alexander.brust@dlr.de, bernd.gruner@dlr.de, noah.erthel@dlr.de
License: BSD-3-Clause
Project-URL: Homepage, https://gitlab.com/dlr-dw/automated-threat-modeling/flowstrider
Platform: any
Classifier: Development Status :: 4 - Beta
Classifier: Programming Language :: Python
Requires-Python: >=3.10
License-File: LICENSE.txt
Requires-Dist: importlib-metadata~=8.7; python_version < "3.8"
Requires-Dist: PyYAML~=6.0
Requires-Dist: marshmallow-dataclass[enum,union]~=8.7
Requires-Dist: marshmallow~=4.0
Requires-Dist: networkx~=3.4
Requires-Dist: openpyxl~=3.1
Requires-Dist: graphviz~=0.21
Requires-Dist: fpdf~=1.7
Requires-Dist: pillow~=12.0
Requires-Dist: colorama~=0.4
Provides-Extra: testing
Requires-Dist: setuptools; extra == "testing"
Requires-Dist: pytest; extra == "testing"
Requires-Dist: pytest-cov; extra == "testing"
Dynamic: license-file
